sources/__init__.py
NuclearDataSampler-0.0.1.dist-info/LICENSE
NuclearDataSampler-0.0.1.dist-info/METADATA
NuclearDataSampler-0.0.1.dist-info/WHEEL
NuclearDataSampler-0.0.1.dist-info/top_level.txt
NuclearDataSampler-0.0.1.dist-info/RECORD
