Metadata-Version: 2.2
Name: NuclearDataSampler
Version: 0.0.1
Summary: Sample Nuclear Data Files
Author-email: SOLE Pierre <pierre.sole@asnr.fr>
License: MIT
Requires-Python: >=3.6
License-File: LICENSE
Requires-Dist: h5py>=3.12.1
Requires-Dist: numpy>=2.2.2
Requires-Dist: pyDOE3>=1.0.4
Requires-Dist: scipy>=1.15.1
